mbf_align-0.5.dist-info/RECORD
mbf_align-0.5.dist-info/LICENSE.txt
mbf_align-0.5.dist-info/AUTHORS.rst
mbf_align-0.5.dist-info/METADATA
mbf_align-0.5.dist-info/WHEEL
mbf_align-0.5.dist-info/top_level.txt
mbf_align/exceptions.py
mbf_align/_common.cpython-38-x86_64-linux-gnu.so
mbf_align/_common.c
mbf_align/post_process.py
mbf_align/fastq2.c
mbf_align/fastq2.cpython-38-x86_64-linux-gnu.so
mbf_align/strategies.py
mbf_align/__init__.py
mbf_align/raw.py
mbf_align/lanes.py
