Metadata-Version: 2.1
Name: mbf_align
Version: 0.5
Summary: Alignment of high througput sequencing data
Home-page: https://github.com/TyberiusPrime/mbf_align
Author: Florian Finkernagel
Author-email: finkernagel@imt.uni-marburg.de
License: mit
Platform: any
Classifier: Development Status :: 4 - Beta
Classifier: Programming Language :: Python
Requires-Python: >=3.6
Provides-Extra: doc
Provides-Extra: testing
